gem/__init__.py
gem/init_setup.py
gem/run_gem.py
gem/analysis/__init__.py
gem/analysis/prf_analysis.py
gem/analysis/prf_r2_variance_explain.py
gem/configs/__init__.py
gem/configs/config_manager.py
gem/configs/gem_xml_utils.py
gem/configs/analysis_configs/analysis_additional_params.h5
gem/configs/analysis_configs/analysis_config.xml
gem/configs/analysis_configs/sample_config.xml
gem/configs/default_config/default_config - old before concatenation.xml
gem/configs/default_config/default_config.xml
gem/configs/default_config/new_concatenationDummyTest_config.xml
gem/configs/default_config/new_concatenation_config.xml
gem/configs/multiproc_prfspace_config/asus_analysis_config.xml
gem/configs/multiproc_prfspace_config/dgx_analysis_config.xml
gem/data/__init__.py
gem/data/bids_handler.py
gem/data/diagnostic_bids_tree.py
gem/data/gem_bids_concatenation_data_info.py
gem/data/gem_bids_individual_run_data_info.py
gem/data/gem_stimulus_file_info.py
gem/data/observed_data.py
gem/fitting/__init__.py
gem/fitting/hpc_coefficient_matrix.py
gem/fitting/hpc_grid_fit.py
gem/fitting/hpc_refine_fit.py
gem/kernels/gaussian_kernel.cu
gem/kernels/gaussian_kernel.ptx
gem/model/__init__.py
gem/model/prf_DoG_model.py
gem/model/prf_gaussian_model.py
gem/model/prf_model.py
gem/model/prf_stimulus.py
gem/model/selected_prf_model.py
gem/run/__init__.py
gem/run/run_gem_prf_analysis.py
gem/signals/__init__.py
gem/signals/hrf_generator.py
gem/signals/orthogonalization_matrix.py
gem/signals/signal_synthesizer.py
gem/space/PRFNeighbours.py
gem/space/PRFSpace.py
gem/space/__init__.py
gem/space/coefficient_matrix.py
gem/tools/__init__.py
gem/tools/json_file_operations.py
gem/utils/__init__.py
gem/utils/assert_no_gemprf.py
gem/utils/gem_gpu_manager.py
gem/utils/gem_h5_file_handler.py
gem/utils/gem_load_estimations.py
gem/utils/gem_write_to_file.py
gem/utils/hpc_cupy_utils.py
gem/utils/logger.py
gemprf/__init__.py
gemprf-0.1.11.dist-info/licenses/LICENSE
gemprf-0.1.11.dist-info/METADATA
gemprf-0.1.11.dist-info/WHEEL
gemprf-0.1.11.dist-info/top_level.txt
gemprf-0.1.11.dist-info/RECORD
