Metadata-Version: 2.4
Name: gemprf
Version: 0.1.11
Summary: A Python library for population receptive field (pRF) analysis
Author-email: Siddharth Mittal <siddharth.mittal@meduniwien.ac.at>
License: BSD 3-Clause License
Project-URL: Homepage, https://gemprf.github.io/
Requires-Python: >=3.8
License-File: LICENSE
Requires-Dist: h5py==3.13.0
Requires-Dist: joblib==1.4.2
Requires-Dist: matplotlib==3.10.1
Requires-Dist: nibabel==5.3.2
Requires-Dist: numba==0.61.0
Requires-Dist: numba_kdtree==0.6.0
Requires-Dist: numpy==2.1.3
Requires-Dist: nvidia_ml_py==12.570.86
Requires-Dist: pandas==2.2.3
Requires-Dist: pynvml==12.0.0
Requires-Dist: scipy==1.15.2
Requires-Dist: xmltodict==0.14.2
Requires-Dist: lxml==5.3.0
Dynamic: license-file
